pyeb/__init__.py
pyeb/__main__.py
pyeb/main.py
pyeb/lib/__init__.py
pyeb/lib/assignment.py
pyeb/lib/context.py
pyeb/lib/event.py
pyeb/lib/machine.py
pyeb/lib/utils.py
pyeb/poporo_translator/ExprContext.py
pyeb/poporo_translator/Python3Lexer.py
pyeb/poporo_translator/Python3LexerBase.py
pyeb/poporo_translator/Python3Parser.py
pyeb/poporo_translator/Python3ParserBase.py
pyeb/poporo_translator/Python3ParserVisitor.py
pyeb/poporo_translator/__init__.py
pyeb/poporo_translator/translator.py
pyeb-1.0.68.dist-info/LICENSE.txt
pyeb-1.0.68.dist-info/METADATA
pyeb-1.0.68.dist-info/WHEEL
pyeb-1.0.68.dist-info/entry_points.txt
pyeb-1.0.68.dist-info/top_level.txt
pyeb-1.0.68.dist-info/RECORD
