Metadata-Version: 2.2
Name: pyeb
Version: 1.0.68
Summary: A refinement calculus implementation of Event-B in Python.
Home-page: https://github.com/ncatanoc/pyeb
Author: Nestor Catano
Author-email: nestor.catano@gmail.com
License: MIT License
Classifier: Development Status :: 2 - Pre-Alpha
Classifier: Environment :: Console
Classifier: Intended Audience :: Developers
Classifier: License :: OSI Approved :: MIT License
Classifier: Operating System :: OS Independent
Classifier: Programming Language :: Python :: 3 :: Only
Classifier: Topic :: Software Development
License-File: LICENSE.txt
Requires-Dist: z3-solver==4.13.0.0
Requires-Dist: antlr4-tools==0.2.1
Requires-Dist: antlr4-python3-runtime>=4.13.1
Dynamic: author
Dynamic: author-email
Dynamic: classifier
Dynamic: description
Dynamic: description-content-type
Dynamic: home-page
Dynamic: license
Dynamic: requires-dist
Dynamic: summary
